django_simple_slack_app/__init__.py
django_simple_slack_app/admin.py
django_simple_slack_app/apps.py
django_simple_slack_app/decorators.py
django_simple_slack_app/emitter.py
django_simple_slack_app/info_cache.py
django_simple_slack_app/migrations/0001_initial.py
django_simple_slack_app/migrations/0002_auto_20211128_1214.py
django_simple_slack_app/migrations/__init__.py
django_simple_slack_app/models.py
django_simple_slack_app/templates/django_simple_slack_app/oauth_done.html
django_simple_slack_app/tests.py
django_simple_slack_app/urls.py
django_simple_slack_app/views.py
django_simple_slack_app-1.0.0.dist-info/LICENSE
django_simple_slack_app-1.0.0.dist-info/WHEEL
django_simple_slack_app-1.0.0.dist-info/METADATA
django_simple_slack_app-1.0.0.dist-info/RECORD
