Metadata-Version: 2.1
Name: django-simple-slack-app
Version: 1.0.0
Summary: nice toolkit for Slack app(bot) that support Event API & OAuth
Author: Matthew, Lee
Author-email: bluedisk@gmail.com
Requires-Python: >=3.7,<4.0
Classifier: Programming Language :: Python :: 3
Classifier: Programming Language :: Python :: 3.10
Classifier: Programming Language :: Python :: 3.7
Classifier: Programming Language :: Python :: 3.8
Classifier: Programming Language :: Python :: 3.9
Requires-Dist: django (>=3.0.4,<4.0.0)
Requires-Dist: hgtk (>=0.1.3,<0.2.0)
Requires-Dist: pyee (>=7.0.1,<8.0.0)
Requires-Dist: slackclient (>=2.5.0,<3.0.0)
Requires-Dist: slackeventsapi (>=2.1.0,<3.0.0)
